singlecell_pipeline/__init__.py
singlecell_pipeline/__main__.py
singlecell_pipeline/config_cli.py
singlecell_pipeline/gene_names.py
singlecell_pipeline/group_de.py
singlecell_pipeline/loader_10x.py
singlecell_pipeline/main_single.py
singlecell_pipeline/markers.py
singlecell_pipeline/pathway_enrichment.py
singlecell_pipeline/pipeline.py
singlecell_pipeline/summary_ct_deg.py
oncocyrix-1.0.1.dist-info/METADATA
oncocyrix-1.0.1.dist-info/WHEEL
oncocyrix-1.0.1.dist-info/entry_points.txt
oncocyrix-1.0.1.dist-info/top_level.txt
oncocyrix-1.0.1.dist-info/RECORD
