Metadata-Version: 2.4
Name: oncocyrix
Version: 1.0.1
Summary: OncoCyrix: a modular Scanpy-based pipeline for single-sample 10x scRNA-seq cancer analysis
Author-email: sheryar_malik <sheryarmalik1403@gmail.com>
Requires-Python: >=3.9
Requires-Dist: scanpy
Requires-Dist: anndata
Requires-Dist: numpy
Requires-Dist: pandas
Requires-Dist: matplotlib
Requires-Dist: scipy
Requires-Dist: gseapy
Requires-Dist: sentence-transformers
Requires-Dist: faiss-cpu
Requires-Dist: mygene
Requires-Dist: celltypist
